<?xml version="1.0"?>
<homework>
<uuid>56e6362d0176443da7ed9db2a9617cee</uuid>
<names>
<name lang="zh-cn">二叉搜索树删除结点测试</name>
 <name lang="en">BST_remove</name>
</names>
<deadlines>
<due>
<timezone>Asia/Shanghai</timezone>
<date>2016-8-19 23:59:59</date>
<scale>1.0</scale>
</due>
<due>
<timezone>Asia/Shanghai</timezone>
<date>2016-8-19 23:59:59</date>
<scale>0.75</scale>
</due>
<due>
<timezone>Asia/Shanghai</timezone>
<date>2016-8-19 23:59:59</date>
<scale>0.5</scale>
</due>
<due>
<timezone>Asia/Shanghai</timezone>
<date>2016-8-19 23:59:59</date>
<scale>0.0</scale>
</due>
</deadlines>
<files />
</homework>